dtit/microFeaturesGenerator/__init__.py
dtit/microFeaturesGenerator/tests/hello.py
dtit/microFeaturesGenerator/tests/test.py
dtit.microFeaturesGenerator-0.0.2.dist-info/LICENSE
dtit.microFeaturesGenerator-0.0.2.dist-info/METADATA
dtit.microFeaturesGenerator-0.0.2.dist-info/WHEEL
dtit.microFeaturesGenerator-0.0.2.dist-info/top_level.txt
dtit.microFeaturesGenerator-0.0.2.dist-info/RECORD
