Metadata-Version: 2.1
Name: dtit.microFeaturesGenerator
Version: 0.0.2
Summary: This is DTIT microFeaturesGenerator library.
Home-page: https://github.com/datatellittech/dtit_packages
Author: sunboss_uw
Author-email: dev@datatellit.com
License: UNKNOWN
Platform: UNKNOWN
Classifier: Programming Language :: Python :: 3
Classifier: License :: OSI Approved :: MIT License
Classifier: Operating System :: OS Independent
Requires-Dist: numpy (>=1.14.0)
